soandso/__init__.py
soandso/core.py
soandso/utils.py
soandso-1.0.0.dist-info/licenses/LICENSE
soandso-1.0.0.dist-info/METADATA
soandso-1.0.0.dist-info/WHEEL
soandso-1.0.0.dist-info/entry_points.txt
soandso-1.0.0.dist-info/top_level.txt
soandso-1.0.0.dist-info/RECORD
