Metadata-Version: 2.4
Name: soandso
Version: 1.0.0
Summary: A collection of delightfully arbitrary utilities
Author-email: Kohan Mathers <mathers.kohan@gmail.com>
License: MIT
Keywords: utilities,tools,fun,arbitrary
Classifier: Development Status :: 4 - Beta
Classifier: Intended Audience :: Developers
Classifier: License :: OSI Approved :: MIT License
Classifier: Programming Language :: Python :: 3
Classifier: Programming Language :: Python :: 3.8
Classifier: Programming Language :: Python :: 3.9
Classifier: Programming Language :: Python :: 3.10
Classifier: Programming Language :: Python :: 3.11
Requires-Python: >=3.8
License-File: LICENSE
Provides-Extra: dev
Requires-Dist: pytest>=6.0; extra == "dev"
Requires-Dist: black; extra == "dev"
Requires-Dist: flake8; extra == "dev"
Requires-Dist: twine; extra == "dev"
Dynamic: license-file
